bde/__init__.py
bde/_version.py
bde/bde.py
bde/bde_builder.py
bde/bde_evaluator.py
bde/task.py
bde/data/__init__.py
bde/data/airfoil.csv
bde/data/concrete.data
bde/data/iris.csv
bde/data/utils.py
bde/loss/__init__.py
bde/loss/loss.py
bde/models/__init__.py
bde/models/models.py
bde/sampler/__init__.py
bde/sampler/callbacks.py
bde/sampler/mile_wrapper.py
bde/sampler/prior.py
bde/sampler/probabilistic.py
bde/sampler/types.py
bde/sampler/utils.py
bde/sampler/warmup.py
bde/tests/__init__.py
bde/tests/test_bde.py
bde/training/__init__.py
bde/training/callbacks.py
bde/training/trainer.py
bde/utils/__init__.py
bde/utils/discovery.py
bde/utils/tests/__init__.py
bde/utils/tests/test_common.py
bde/utils/tests/test_discovery.py
sklearn_contrib_bde-1.0.1.dist-info/licenses/LICENSE
sklearn_contrib_bde-1.0.1.dist-info/METADATA
sklearn_contrib_bde-1.0.1.dist-info/WHEEL
sklearn_contrib_bde-1.0.1.dist-info/top_level.txt
sklearn_contrib_bde-1.0.1.dist-info/RECORD
