Metadata-Version: 2.4
Name: sklearn-contrib-bde
Version: 1.0.1
Summary: Bayesian Deep Ensembles with MILE (JAX), scikit-learn style.
Author-email: Arvanitis Vyron <vyronas.arvanitis@gmail.com>, Aslanidis Angelos <angelo.aslanidis@gmail.com>, Sommer Emanuel <emanuel.sommer@stat.uni-muenchen.de>
Project-URL: Homepage, https://github.com/scikit-learn-contrib/bde
Project-URL: Issues, https://github.com/scikit-learn-contrib/bde/issues
Classifier: Programming Language :: Python :: 3
Classifier: Programming Language :: Python :: 3.9
Classifier: Programming Language :: Python :: 3.10
Classifier: Programming Language :: Python :: 3.11
Classifier: Programming Language :: Python :: 3.12
Classifier: License :: OSI Approved :: BSD License
Classifier: Operating System :: POSIX
Classifier: Operating System :: Unix
Classifier: Operating System :: MacOS
Classifier: Operating System :: Microsoft :: Windows
Requires-Python: >=3.9
License-File: LICENSE
Requires-Dist: numpy>=1.26.4
Requires-Dist: scipy>=1.16.2
Requires-Dist: scikit-learn>=1.7.2
Requires-Dist: jax>=0.4.28
Requires-Dist: jaxlib>=0.4.28
Requires-Dist: optax>=0.2.1
Requires-Dist: blackjax==1.2.2
Requires-Dist: tqdm>=4.67.1
Requires-Dist: ipython>=8.0
Dynamic: license-file
